{
  "version": "3.7.14",
  "timestamp": 1771831740753,
  "config": {
    "parallel": true,
    "workers": 7,
    "timeout": 8371,
    "retries": 4
  },
  "metadata": {
    "id": "commit-99-fp9q8",
    "hash": "n1exxd",
    "environment": "production"
  },
  "features": [
    {
      "name": "06x9we",
      "enabled": false
    },
    {
      "name": "jzk35m",
      "enabled": true
    },
    {
      "name": "8nkvhd",
      "enabled": false
    },
    {
      "name": "98ofs",
      "enabled": false
    },
    {
      "name": "wdccqs",
      "enabled": true
    }
  ]
}