{
  "version": "1.19.25",
  "timestamp": 1771831740762,
  "config": {
    "parallel": false,
    "workers": 7,
    "timeout": 25145,
    "retries": 2
  },
  "metadata": {
    "id": "commit-159-nws5m9",
    "hash": "yteenn",
    "environment": "production"
  },
  "features": [
    {
      "name": "8qnpmg",
      "enabled": true
    },
    {
      "name": "789eq",
      "enabled": true
    },
    {
      "name": "hpndne",
      "enabled": true
    },
    {
      "name": "svqggk",
      "enabled": true
    },
    {
      "name": "5e5rtl",
      "enabled": false
    }
  ]
}