{
  "version": "2.8.89",
  "timestamp": 1771831740803,
  "config": {
    "parallel": true,
    "workers": 4,
    "timeout": 7892,
    "retries": 2
  },
  "metadata": {
    "id": "commit-424-xj7s8u",
    "hash": "vfdck",
    "environment": "production"
  },
  "features": [
    {
      "name": "yt7k",
      "enabled": true
    },
    {
      "name": "n876y",
      "enabled": true
    },
    {
      "name": "idej8",
      "enabled": true
    },
    {
      "name": "csdm9g",
      "enabled": false
    },
    {
      "name": "2trqhf",
      "enabled": true
    }
  ]
}