{
  "version": "1.11.60",
  "timestamp": 1771831740829,
  "config": {
    "parallel": true,
    "workers": 1,
    "timeout": 5331,
    "retries": 3
  },
  "metadata": {
    "id": "commit-583-gichge",
    "hash": "ctc92g",
    "environment": "production"
  },
  "features": [
    {
      "name": "xht2tc",
      "enabled": true
    },
    {
      "name": "n1uins",
      "enabled": true
    },
    {
      "name": "is79m",
      "enabled": true
    },
    {
      "name": "9ovx",
      "enabled": true
    },
    {
      "name": "tj9d6d",
      "enabled": true
    }
  ]
}