{
  "version": "0.3.37",
  "timestamp": 1771831740804,
  "config": {
    "parallel": true,
    "workers": 5,
    "timeout": 29068,
    "retries": 4
  },
  "metadata": {
    "id": "commit-432-90ybv",
    "hash": "ivdcv9",
    "environment": "production"
  },
  "features": [
    {
      "name": "la0sks",
      "enabled": false
    },
    {
      "name": "5rcc1",
      "enabled": true
    },
    {
      "name": "jk4zn5",
      "enabled": true
    },
    {
      "name": "t9iv29",
      "enabled": false
    },
    {
      "name": "s7c1m7",
      "enabled": false
    }
  ]
}