{
  "version": "0.13.55",
  "timestamp": 1771831740887,
  "config": {
    "parallel": true,
    "workers": 8,
    "timeout": 13091,
    "retries": 4
  },
  "metadata": {
    "id": "commit-947-nco6zq",
    "hash": "pxgqde",
    "environment": "production"
  },
  "features": [
    {
      "name": "lrztsj",
      "enabled": true
    },
    {
      "name": "eszh5",
      "enabled": false
    },
    {
      "name": "weavrj",
      "enabled": true
    },
    {
      "name": "o278ng",
      "enabled": true
    },
    {
      "name": "gyw1m8",
      "enabled": true
    }
  ]
}