{
  "version": "1.1.6",
  "timestamp": 1771831740743,
  "config": {
    "parallel": false,
    "workers": 5,
    "timeout": 25224,
    "retries": 4
  },
  "metadata": {
    "id": "commit-53-dq44gk",
    "hash": "x5h4",
    "environment": "production"
  },
  "features": [
    {
      "name": "j4yymj",
      "enabled": true
    },
    {
      "name": "u5oc4",
      "enabled": false
    },
    {
      "name": "03we48",
      "enabled": false
    },
    {
      "name": "px6i3q",
      "enabled": false
    },
    {
      "name": "j1hx2",
      "enabled": true
    }
  ]
}