{
  "version": "3.14.62",
  "timestamp": 1771831740877,
  "config": {
    "parallel": true,
    "workers": 2,
    "timeout": 26266,
    "retries": 3
  },
  "metadata": {
    "id": "commit-878-viok1m",
    "hash": "rk0l",
    "environment": "production"
  },
  "features": [
    {
      "name": "6obx3",
      "enabled": true
    },
    {
      "name": "ijei5o",
      "enabled": true
    },
    {
      "name": "sfkzae",
      "enabled": true
    },
    {
      "name": "uruz83",
      "enabled": true
    },
    {
      "name": "cf6y7",
      "enabled": true
    }
  ]
}